sourpea/__init__.py
sourpea/primitives.py
sourpea/util.py
sourpea-0.0.9.dist-info/METADATA
sourpea-0.0.9.dist-info/WHEEL
sourpea-0.0.9.dist-info/RECORD
